{
  "date": "2026-04-14",
  "major_issues": [],
  "voc_groups": [
    {
      "semantic_topic": "기타",
      "issue_type": "게임 일반",
      "category": "기타",
      "summary": "엡 업뎃중 팅거서 게임을 못하고잇어여 엘디플레이어로 게임을 하고 잇는 유저입니다 어제 저녁부터 게임을 못하고",
      "count": 2,
      "representative_url": "https://game.naver.com/lounge/DK_Mobile_REBORN/board/detail/7535677",
      "feed_ids": [
        "7535677",
        "7537569"
      ]
    }
  ],
  "insights": {
    "top_issues": [
      {
        "category": "기타",
        "summary": "엡 업뎃중 팅거서 게임을 못하고잇어여 엘디플레이어로 게임을 하고 잇는 유저입니다 어제 저녁부터 게임을 못하고",
        "count": 2,
        "url": "https://game.naver.com/lounge/DK_Mobile_REBORN/board/detail/7535677"
      }
    ],
    "trend": {
      "기타": {
        "current": 2,
        "previous": 4,
        "delta": -2
      }
    },
    "trending_keywords": [],
    "prev_date": "2026-04-13"
  },
  "cs_daily": {
    "received": 1,
    "processed": 3
  },
  "cs_status_counts": {
    "답변 완료": 35,
    "삭제": 1,
    "조회 완료": 31
  },
  "cs_inquiries": [
    {
      "category": "기타",
      "count": 1,
      "pending": 0,
      "representative": [
        {
          "title": "연합이안됩니다",
          "body": "캐릭터명 : 빅토리는패는맛 서버명 : 나크로바스 둠스카일서버 RedDevil 연합에 들어가려고하는데 연합검색자체가 안되고요 레드데빌에서 연합초대가와도 신청목록에 들어가면 목록이 없어집니다",
          "status": "답변 완료",
          "date": "2026-04-14"
        }
      ]
    }
  ],
  "cs_week_trend": [
    {
      "date": "2026-04-08",
      "received": 0,
      "processed": 0
    },
    {
      "date": "2026-04-09",
      "received": 0,
      "processed": 0
    },
    {
      "date": "2026-04-10",
      "received": 0,
      "processed": 0
    },
    {
      "date": "2026-04-11",
      "received": 0,
      "processed": 0
    },
    {
      "date": "2026-04-12",
      "received": 0,
      "processed": 0
    },
    {
      "date": "2026-04-13",
      "received": 5,
      "processed": 2
    },
    {
      "date": "2026-04-14",
      "received": 1,
      "processed": 3
    }
  ]
}